hou-stubs/__init__.pyi
hou-stubs/py.typed
types_houdini-21.0.512.3.dist-info/METADATA
types_houdini-21.0.512.3.dist-info/WHEEL
types_houdini-21.0.512.3.dist-info/RECORD
